easy_edge_tts/__init__.py
easy_edge_tts/rotator.py
easy_edge_tts/tts.py
easy_edge_tts/utils.py
easy_edge_tts/voices.py
easy_edge_tts-0.4.0.dist-info/METADATA
easy_edge_tts-0.4.0.dist-info/WHEEL
easy_edge_tts-0.4.0.dist-info/licenses/LICENSE
easy_edge_tts-0.4.0.dist-info/RECORD
