Metadata-Version: 2.4
Name: easy-edge-tts
Version: 0.4.0
Summary: High-level TTS with voice rotation and mood selection for content creators
Project-URL: Homepage, https://github.com/YanivGabay/easy-edge-tts
Project-URL: Documentation, https://github.com/YanivGabay/easy-edge-tts#readme
Project-URL: Repository, https://github.com/YanivGabay/easy-edge-tts
Project-URL: Issues, https://github.com/YanivGabay/easy-edge-tts/issues
Author: Yaniv Gabay
License-Expression: MIT
License-File: LICENSE
Keywords: audio,content-creation,edge-tts,elevenlabs,podcast,text-to-speech,tiktok,tts,voice,youtube
Classifier: Development Status :: 4 - Beta
Classifier: Intended Audience :: Developers
Classifier: License :: OSI Approved :: MIT License
Classifier: Operating System :: OS Independent
Classifier: Programming Language :: Python :: 3
Classifier: Programming Language :: Python :: 3.10
Classifier: Programming Language :: Python :: 3.11
Classifier: Programming Language :: Python :: 3.12
Classifier: Topic :: Multimedia :: Sound/Audio :: Speech
Classifier: Topic :: Software Development :: Libraries :: Python Modules
Requires-Python: >=3.10
Requires-Dist: edge-tts>=6.1.0
Provides-Extra: all
Requires-Dist: httpx>=0.25.0; extra == 'all'
Provides-Extra: dev
Requires-Dist: pytest-asyncio>=0.21.0; extra == 'dev'
Requires-Dist: pytest>=7.0.0; extra == 'dev'
Requires-Dist: ruff>=0.1.0; extra == 'dev'
Provides-Extra: elevenlabs
Requires-Dist: httpx>=0.25.0; extra == 'elevenlabs'
